zeus_utility/__init__.py
zeus_utility/embeddings.py
zeus_utility/io.py
zeus_utility/parallel_executor.py
zeus_utility-0.1.0.dist-info/LICENSE
zeus_utility-0.1.0.dist-info/METADATA
zeus_utility-0.1.0.dist-info/WHEEL
zeus_utility-0.1.0.dist-info/top_level.txt
zeus_utility-0.1.0.dist-info/RECORD
