Metadata-Version: 2.1
Name: zeus-utility
Version: 0.1.0
Summary: Just some useful utilities Zeus will use in almost every projects.
Home-page: https://github.com/zeuscsc/zeus_utility.git
Author: Zeus Chiu
Author-email: zeuscsc@gmail.com
License: MIT
Classifier: License :: OSI Approved :: MIT License
Classifier: Programming Language :: Python
Classifier: Programming Language :: Python :: 3
Classifier: Programming Language :: Python :: 3.6
Classifier: Programming Language :: Python :: Implementation :: CPython
Classifier: Programming Language :: Python :: Implementation :: PyPy
Requires-Python: >=3.9.0
License-File: LICENSE
Requires-Dist: pypdf ==4.2.0
Requires-Dist: tqdm ==4.66.4
